gqlrequests_api_tibber/__init__.py
gqlrequests_api_tibber-0.0.1.dist-info/LICENSE
gqlrequests_api_tibber-0.0.1.dist-info/METADATA
gqlrequests_api_tibber-0.0.1.dist-info/WHEEL
gqlrequests_api_tibber-0.0.1.dist-info/top_level.txt
gqlrequests_api_tibber-0.0.1.dist-info/RECORD
