Metadata-Version: 2.1
Name: gqlrequests-api-tibber
Version: 0.0.1
Summary: Dataclasses for all GraphQL queries, subscriptions and mutations for Tibber API. Meant to be used with gqlrequests.
Author: BeatsuDev
Project-URL: Homepage, https://github.com/BeatsuDev/gqlrequests-api-tibber
Project-URL: Bug Tracker, https://github.com/BeatsuDev/gqlrequests-api-tibber/issues
Classifier: Development Status :: 1 - Planning
Classifier: Intended Audience :: Developers
Classifier: Programming Language :: Python :: 3
Classifier: License :: OSI Approved :: MIT License
Classifier: Operating System :: OS Independent
Classifier: Topic :: Software Development :: Libraries :: Python Modules
Requires-Python: >=3.7
License-File: LICENSE
